dtxlog/__init__.py
dtxlog/_compat.py
dtxlog/config.py
dtxlog/formatters.py
dtxlog/handlers.py
dtxlog/level.py
dtxlog-0.1.1.dist-info/WHEEL
dtxlog-0.1.1.dist-info/METADATA
dtxlog-0.1.1.dist-info/RECORD
