Metadata-Version: 2.1
Name: dtxlog
Version: 0.1.1
Summary: 
Author: Youngbok Yoon
Author-email: bok@weltcorp.com
Requires-Python: >=3.7,<4.0
Classifier: Programming Language :: Python :: 3
Classifier: Programming Language :: Python :: 3.10
Classifier: Programming Language :: Python :: 3.7
Classifier: Programming Language :: Python :: 3.8
Classifier: Programming Language :: Python :: 3.9
Requires-Dist: pydantic (>=1.9.0,<2.0.0)
Requires-Dist: python-dotenv (>=0.20.0,<0.21.0)
Requires-Dist: redis (>=4.3.1,<5.0.0)
